pdf417gen/__init__.py
pdf417gen/__main__.py
pdf417gen/codes.py
pdf417gen/console.py
pdf417gen/data.py
pdf417gen/encoding.py
pdf417gen/error_correction.py
pdf417gen/rendering.py
pdf417gen/util.py
pdf417gen/compaction/__init__.py
pdf417gen/compaction/byte.py
pdf417gen/compaction/numeric.py
pdf417gen/compaction/optimizations.py
pdf417gen/compaction/text.py
pdf417gen-0.8.0.dist-info/LICENSE
pdf417gen-0.8.0.dist-info/METADATA
pdf417gen-0.8.0.dist-info/WHEEL
pdf417gen-0.8.0.dist-info/entry_points.txt
pdf417gen-0.8.0.dist-info/top_level.txt
pdf417gen-0.8.0.dist-info/RECORD
