Metadata-Version: 2.1
Name: pdf417gen
Version: 0.8.0
Summary: PDF417 2D barcode generator for Python
Author-email: Ivan Habunek <ivan@habunek.com>
License: PDF417-Py License
Project-URL: Homepage, https://github.com/ihabunek/pdf417-py/
Keywords: pdf417,2d,barcode,generator
Classifier: Programming Language :: Python :: 3
Classifier: License :: OSI Approved :: MIT License
Classifier: Operating System :: OS Independent
Classifier: Environment :: Console
Requires-Python: >=3.8
License-File: LICENSE
Requires-Dist: Pillow >=3.3.0
Provides-Extra: dev
Requires-Dist: build ; extra == 'dev'
Requires-Dist: twine ; extra == 'dev'
Provides-Extra: test
Requires-Dist: mock ; extra == 'test'
Requires-Dist: pytest ; extra == 'test'
Requires-Dist: pytest-cov ; extra == 'test'
Requires-Dist: vermin ; extra == 'test'
